modrinth/__init__.py
modrinth/__main__.py
Modrinth_API-0.0.1.dist-info/METADATA
Modrinth_API-0.0.1.dist-info/WHEEL
Modrinth_API-0.0.1.dist-info/top_level.txt
Modrinth_API-0.0.1.dist-info/RECORD
