Metadata-Version: 2.1
Name: Modrinth-API
Version: 0.0.1
Summary: A no-compromises wrapper for the Modrinth API
Home-page: https://github.com/Advik-B/modrinth-api
Author: Advik
Author-email: <advik.b@gmail.com>
Keywords: CMPDL,Minecraft,Modrinth,API,Wrapper
Classifier: Intended Audience :: Developers
Classifier: Programming Language :: Python :: 3
Classifier: License :: OSI Approved :: MIT License
Classifier: Operating System :: OS Independent
Requires-Dist: requests
